flatten_nested/__init__.py
flatten_nested/exceptions.py
flatten_nested/flattener.py
flatten_nested/tests/__init__.py
flatten_nested/tests/test_flattener.py
flatten_nested/utils.py
flatten_nested-0.1.1.dist-info/LICENSE
flatten_nested-0.1.1.dist-info/METADATA
flatten_nested-0.1.1.dist-info/WHEEL
flatten_nested-0.1.1.dist-info/RECORD
