Metadata-Version: 2.1
Name: flatten-nested
Version: 0.1.1
Summary: A Python package to flatten nested data structures
Home-page: https://github.com/sathishpatel415/flatten_nested
License: MIT
Keywords: flatten,nested,list,dict,tuple,set
Author: Sathish Kumar K
Author-email: sathishpatel415@gmail.com
Requires-Python: >=3.8,<4.0
Classifier: Development Status :: 3 - Alpha
Classifier: Intended Audience :: Developers
Classifier: License :: OSI Approved :: MIT License
Classifier: Programming Language :: Python :: 3
Classifier: Programming Language :: Python :: 3.8
Classifier: Programming Language :: Python :: 3.9
Classifier: Programming Language :: Python :: 3.10
Classifier: Programming Language :: Python :: 3.11
Classifier: Programming Language :: Python :: 3.12
Classifier: Programming Language :: Python :: 3.13
Classifier: Programming Language :: Python :: 3.7
Project-URL: Documentation, https://github.com/sathishpatel415/flatten_nested#readme
Project-URL: Repository, https://github.com/sathishpatel415/flatten_nested
